async_crypto_pay_api/__init__.py
async_crypto_pay_api/__meta__.py
async_crypto_pay_api/client.py
async_crypto_pay_api/exceptions.py
async_crypto_pay_api/models/__init__.py
async_crypto_pay_api/models/app_info.py
async_crypto_pay_api/models/app_stats.py
async_crypto_pay_api/models/assets.py
async_crypto_pay_api/models/balance.py
async_crypto_pay_api/models/check.py
async_crypto_pay_api/models/currency.py
async_crypto_pay_api/models/exchange_rate.py
async_crypto_pay_api/models/invoice.py
async_crypto_pay_api/models/items.py
async_crypto_pay_api/models/response.py
async_crypto_pay_api/models/transfer.py
async_crypto_pay_api-1.1.0.dist-info/METADATA
async_crypto_pay_api-1.1.0.dist-info/WHEEL
async_crypto_pay_api-1.1.0.dist-info/licenses/LICENSE
async_crypto_pay_api-1.1.0.dist-info/RECORD
