Metadata-Version: 2.4
Name: async-crypto-pay-api
Version: 1.1.0
Summary: Async crypto pay api wrapper for t.me/cryptobot
Project-URL: repository, https://codeberg.org/igorechek06/async_crypto_pay_api
Project-URL: documentation, https://help.send.tg/en/articles/10279948-crypto-pay-api
Author-email: Tolmachev Igor <me@igorek.dev>
Maintainer-email: Tolmachev Igor <me@igorek.dev>
License-Expression: LGPL-3.0-only
License-File: LICENSE
Keywords: api,async,crypto,crypto pay api,cryptobot
Classifier: Framework :: AsyncIO
Classifier: License :: OSI Approved :: GNU Lesser General Public License v3 (LGPLv3)
Classifier: Programming Language :: Python
Classifier: Programming Language :: Python :: 3
Classifier: Programming Language :: Python :: 3.10
Classifier: Programming Language :: Python :: 3.11
Classifier: Programming Language :: Python :: 3.12
Classifier: Programming Language :: Python :: 3.13
Classifier: Programming Language :: Python :: 3.14
Classifier: Programming Language :: Python :: 3.15
Classifier: Typing :: Typed
Requires-Python: >=3.10
Requires-Dist: aiohttp>=3.12.14
Requires-Dist: pydantic>=2.11.7
